{
  "kind": "collectionType",
  "collectionName": "posts",
  "info": {
    "singularName": "post",
    "pluralName": "posts",
    "displayName": "Post",
    "description": ""
  },
  "options": {
    "draftAndPublish": true
  },
  "pluginOptions": {},
  "attributes": {
    "title": {
      "type": "string"
    },
    "excerpt": {
      "type": "string"
    },
    "author": {
      "type": "string"
    },
    "date": {
      "type": "date"
    },
    "featured_image": {
      "type": "media",
      "multiple": false,
      "required": false,
      "allowedTypes": [
        "images"
      ]
    },
    "post_number": {
      "type": "integer"
    },
    "slug": {
      "type": "uid",
      "targetField": "title"
    },
    "content": {
      "type": "richtext"
    }
  }
}
